opencerebro/agents/toolformer/__init__.py
opencerebro_agent_toolformer-0.1.2.dist-info/METADATA
opencerebro_agent_toolformer-0.1.2.dist-info/WHEEL
opencerebro_agent_toolformer-0.1.2.dist-info/RECORD
